pwcnet/__init__.py
pwcnet/correlation.py
pwcnet/model.py
pwcnet/run_pair.py
pwcnet/run_video.py
pwcnet/utils.py
pwcnet/visualize.py
pwcnet-0.2.dist-info/LICENSE
pwcnet-0.2.dist-info/METADATA
pwcnet-0.2.dist-info/WHEEL
pwcnet-0.2.dist-info/top_level.txt
pwcnet-0.2.dist-info/RECORD
